README.rst
setup.cfg
setup.py
appspiderproapi/__init__.py
appspiderproapi/appspiderpro.py
appspiderproapi.egg-info/PKG-INFO
appspiderproapi.egg-info/SOURCES.txt
appspiderproapi.egg-info/dependency_links.txt
appspiderproapi.egg-info/requires.txt
appspiderproapi.egg-info/top_level.txt
appspiderproapi.egg-info/zip-safe