Metadata-Version: 1.1
Name: appspiderproapi
Version: 0.0.1b0
Summary: Python library for AppSpider Professional RESTFul API endpoints.
Home-page: https://github.com/xolian/appspiderproapi
Author: Brandon Spruth
Author-email: brandon@spruth.co
License: MIT
Download-URL: https://github.com/xolian/appspiderproapi/tarball/0.0.1b
Keywords: appspider,api,security,software,rapid7,appspiderpro,ntobjectives,dast
Platform: UNKNOWN
Classifier: Development Status :: 4 - Beta
Classifier: Intended Audience :: Developers
Classifier: Natural Language :: English
Classifier: License :: OSI Approved :: MIT License
Classifier: Topic :: Software Development
Classifier: Topic :: Software Development :: Libraries :: Python Modules
Classifier: Programming Language :: Python :: 3.0
Classifier: Programming Language :: Python :: 3.7
